{"stat.useItem.minecraft.brick_stairs":707,"stat.useItem.minecraft.quartz_block":1605,"stat.leaveGame":19,"stat.useItem.minecraft.diamond_sword":158,"stat.useItem.minecraft.glowstone":456,"stat.swimOneCm":4192,"stat.useItem.minecraft.planks":19,"stat.pickup.minecraft.glowstone":1,"stat.useItem.minecraft.end_rod":8,"stat.pickup.minecraft.porkchop":17,"stat.useItem.minecraft.obsidian":1,"stat.useItem.minecraft.dirt":1142,"stat.useItem.minecraft.stone_slab2":1346,"stat.useItem.minecraft.golden_sword":75,"stat.pickup.minecraft.brick_block":1,"stat.killEntity.Donkey":1,"stat.drop.minecraft.brick_block":1,"stat.pickup.minecraft.name_tag":64,"stat.pickup.minecraft.cobblestone":4,"stat.pickup.minecraft.diamond_leggings":1,"stat.useItem.minecraft.brick_block":1118,"stat.flyOneCm":9539295,"stat.drop.minecraft.wheat_seeds":2,"stat.drop.minecraft.gold_ingot":1,"stat.timeSinceDeath":130328,"stat.useItem.minecraft.fence_gate":3,"stat.useItem.minecraft.spawn_egg":4,"stat.pickup.minecraft.mutton":9,"stat.pickup.vehicle.vehicle_crate":4,"stat.pickup.minecraft.wooden_axe":4,"stat.drop.minecraft.iron_bars":4,"stat.pickup.minecraft.dark_oak_door":3,"stat.drop.minecraft.stained_glass":1,"stat.drop.minecraft.diamond_block":1,"stat.pickup.minecraft.carpet":1,"stat.drop.minecraft.stone_slab":5,"stat.pickup.minecraft.beef":11,"stat.sprintOneCm":84140,"stat.drop.minecraft.potion":1,"stat.pickup.minecraft.acacia_door":1,"stat.useItem.minecraft.dark_oak_door":69,"stat.useItem.minecraft.stone_slab":1364,"stat.killEntity.Horse":9,"stat.useItem.minecraft.bed":3,"stat.pickup.minecraft.potion":1,"stat.pickup.minecraft.fireworks":1,"stat.useItem.minecraft.flint_and_steel":7,"stat.pickup.minecraft.grass":3,"stat.pickup.minecraft.diamond_chestplate":1,"stat.pickup.minecraft.saddle":1,"stat.useItem.minecraft.dye":65,"stat.pickup.minecraft.spawn_egg":1,"stat.deaths":6,"stat.drop":50,"stat.pickup.minecraft.egg":3,"stat.playOneMinute":1150549,"stat.killEntity.Sheep":3,"stat.useItem.minecraft.nether_brick":6,"stat.pickup.minecraft.iron_bars":4,"stat.diveOneCm":300,"stat.pickup.minecraft.sign":4,"stat.useItem.minecraft.stone":1,"stat.useItem.minecraft.quartz_stairs":47,"stat.pickup.minecraft.stained_glass_pane":2,"stat.useItem.minecraft.carpet":16,"stat.useItem.minecraft.stained_glass_pane":1121,"stat.pickup.minecraft.brick_stairs":1,"stat.pickup.minecraft.diamond_sword":2,"stat.jump":2796,"stat.pickup.minecraft.fence":1,"stat.drop.minecraft.diamond_sword":2,"stat.crouchOneCm":6081,"stat.drop.minecraft.gold_ore":1,"stat.pickup.minecraft.dirt":53,"stat.drop.minecraft.glowstone":1,"stat.craftingTableInteraction":1,"stat.drop.minecraft.stained_glass_pane":3,"stat.useItem.minecraft.glass":14,"stat.pickup.minecraft.heavy_weighted_pressure_plate":1,"stat.useItem.minecraft.sapling":6,"stat.pickup.minecraft.comparator":13,"stat.pickup.minecraft.leather":15,"stat.damageTaken":2015,"stat.pickup.minecraft.feather":6,"stat.drop.minecraft.concrete":13,"stat.useItem.minecraft.acacia_door":1,"stat.noteblockTuned":1,"stat.pickup.minecraft.planks":3,"stat.pickup.minecraft.concrete":12,"stat.pickup.minecraft.wheat_seeds":2,"stat.pickup.minecraft.potato":5,"stat.pickup.minecraft.lead":2,"stat.damageDealt":5065,"stat.killEntity.Cow":7,"stat.killEntity.Pig":11,"stat.useItem.minecraft.iron_bars":106,"stat.walkOneCm":2447586,"stat.drop.minecraft.porkchop":1,"stat.useItem.minecraft.tnt":44,"stat.drop.minecraft.sign":2,"stat.pickup.minecraft.bedrock":1,"stat.pickup.minecraft.stone":1,"stat.pickup.minecraft.chicken":4,"stat.useItem.minecraft.stained_hardened_clay":202,"stat.drop.minecraft.brick_stairs":2,"stat.pickup.minecraft.sapling":1,"stat.useItem.minecraft.leaves":389,"stat.useItem.minecraft.concrete":4473,"stat.useItem.minecraft.fireworks":1016,"stat.pickup.minecraft.gold_ingot":89,"stat.useItem.minecraft.birch_door":2,"stat.killEntity.Chicken":4,"stat.pickup.minecraft.diamond_helmet":1,"stat.mobKills":37,"stat.killEntity.Mule":2,"stat.pickup.minecraft.book":2,"stat.pickup.minecraft.diamond_boots":1,"stat.drop.props.props":4,"stat.pickup.minecraft.birch_fence":1,"stat.pickup.props.props":1,"stat.pickup.minecraft.red_flower":1,"stat.sneakTime":6471,"stat.pickup.minecraft.wool":5,"stat.drop.minecraft.quartz_block":2,"stat.pickup.minecraft.stone_slab":5,"stat.drop.minecraft.grass":2,"stat.pickup.minecraft.trapped_chest":1,"stat.drop.minecraft.wooden_axe":3}